bilkent_traffic.py
bilkent_traffic-0.7.4.dist-info/LICENSE
bilkent_traffic-0.7.4.dist-info/METADATA
bilkent_traffic-0.7.4.dist-info/WHEEL
bilkent_traffic-0.7.4.dist-info/entry_points.txt
bilkent_traffic-0.7.4.dist-info/top_level.txt
bilkent_traffic-0.7.4.dist-info/RECORD
