Metadata-Version: 2.1
Name: bilkent-traffic
Version: 0.7.4
Summary: A Python package for sending traffic violation reports via Bilkent email
Home-page: https://github.com/onurcangnc/bilkent_traffic
Author: Onurcan Genç
Author-email: onurcan.genc@ug.bilkent.edu.tr
License: MIT
License-File: LICENSE
Requires-Dist: pyfiglet
Requires-Dist: pillow
